bookstack_file_exporter/__init__.py
bookstack_file_exporter/__main__.py
bookstack_file_exporter/run.py
bookstack_file_exporter/run_args.py
bookstack_file_exporter/archiver/__init__.py
bookstack_file_exporter/archiver/archiver.py
bookstack_file_exporter/archiver/asset_archiver.py
bookstack_file_exporter/archiver/minio_archiver.py
bookstack_file_exporter/archiver/page_archiver.py
bookstack_file_exporter/archiver/util.py
bookstack_file_exporter/common/__init__.py
bookstack_file_exporter/common/util.py
bookstack_file_exporter/config_helper/__init__.py
bookstack_file_exporter/config_helper/config_helper.py
bookstack_file_exporter/config_helper/models.py
bookstack_file_exporter/config_helper/notifications.py
bookstack_file_exporter/config_helper/remote.py
bookstack_file_exporter/exporter/__init__.py
bookstack_file_exporter/exporter/exporter.py
bookstack_file_exporter/exporter/node.py
bookstack_file_exporter/notify/__init__.py
bookstack_file_exporter/notify/handler.py
bookstack_file_exporter/notify/notifiers.py
bookstack_file_exporter-1.6.0.dist-info/licenses/LICENSE
bookstack_file_exporter-1.6.0.dist-info/METADATA
bookstack_file_exporter-1.6.0.dist-info/WHEEL
bookstack_file_exporter-1.6.0.dist-info/entry_points.txt
bookstack_file_exporter-1.6.0.dist-info/top_level.txt
bookstack_file_exporter-1.6.0.dist-info/RECORD
