Metadata-Version: 2.4
Name: bookstack-file-exporter
Version: 1.6.0
Summary: An exporter written in python to export all documents from a bookstack instance in different formats
Home-page: https://github.com/homeylab/bookstack-file-exporter
Author: pchang388
License: MIT License
Keywords: bookstack,exporter
Classifier: License :: OSI Approved :: MIT License
Classifier: Programming Language :: Python :: 3
Requires-Python: >=3.8
License-File: LICENSE
Requires-Dist: Pyyaml>=6.0.2
Requires-Dist: Pydantic>=2.10.6
Requires-Dist: requests>=2.32.3
Requires-Dist: minio>=7.2.15
Requires-Dist: apprise>=1.9.4
Dynamic: license-file
